custom_model/__init__.py
custom_model/custom_model.py
custom_model-0.2.dist-info/METADATA
custom_model-0.2.dist-info/WHEEL
custom_model-0.2.dist-info/top_level.txt
custom_model-0.2.dist-info/RECORD
